ic_id/__init__.py
ic_id/core.py
ic_id/template/And.png
ic_id/template/And3.png
ic_id/template/And4.png
ic_id/template/HLAlm-H.png
ic_id/template/HLAlm-L.png
ic_id/template/Not.png
ic_id/template/Or.png
ic_id/template/Or3.png
ic_id/template/Or4.png
ic_id/template/Pulse.png
ic_id/template/SFT.png
ic_id/template/TDOn.png
ic_id-0.1.0b0.dist-info/METADATA
ic_id-0.1.0b0.dist-info/WHEEL
ic_id-0.1.0b0.dist-info/top_level.txt
ic_id-0.1.0b0.dist-info/RECORD
