Metadata-Version: 2.4
Name: ic_id
Version: 0.1.0b0
Requires-Python: >=3.9
Requires-Dist: opencv-python>=4.5.0
Requires-Dist: numpy>=1.21.0
